<?xml version="1.0" encoding="UTF-8"?>
<doi_batch xmlns="http://www.crossref.org/schema/4.4.0" xmlns:ai="http://www.crossref.org/AccessIndicators.xsd" xmlns:rel="http://www.crossref.org/relations.xsd" xmlns:xsi="http://www.w3.org/2001/XMLSchema-instance" version="4.4.0" xsi:schemaLocation="http://www.crossref.org/schema/4.4.0 http://www.crossref.org/schemas/crossref4.4.0.xsd">
  <head>
    <doi_batch_id>1a6a9f17a838d2a02505950dee52fd9a</doi_batch_id>
    <timestamp>20180621121146</timestamp>
    <depositor>
      <depositor_name>JOSS Admin</depositor_name>
      <email_address>admin@theoj.org</email_address>
    </depositor>
    <registrant>The Open Journal</registrant>
  </head>
  <body>
    <journal>
      <journal_metadata>
        <full_title>Journal of Open Source Software</full_title>
        <abbrev_title>JOSS</abbrev_title>
        <issn media_type="electronic">2475-9066</issn>
        <doi_data>
          <doi>10.21105/joss</doi>
          <resource>http://joss.theoj.org</resource>
        </doi_data>
      </journal_metadata>
      <journal_issue>
        <publication_date media_type="online">
          <month>06</month>
          <year>2018</year>
        </publication_date>
        <journal_volume>
          <volume>3</volume>
        </journal_volume>
        <issue>26</issue>
      </journal_issue>
      <journal_article publication_type="full_text">
        <titles>
          <title>MatchPy: Pattern Matching in Python</title>
        </titles>
        <contributors><person_name sequence="first" contributor_role="author"><given_name>Manuel</given_name><surname>Krebber</surname><ORCID>http://orcid.org/0000-0001-5038-1102</ORCID></person_name><person_name sequence="additional" contributor_role="author"><given_name>Henrik</given_name><surname>Barthels</surname><ORCID>http://orcid.org/0000-0001-6744-3605</ORCID></person_name></contributors>
        <publication_date>
          <month>06</month>
          <day>21</day>
          <year>2018</year>
        </publication_date>
        <pages>
          <first_page>670</first_page>
        </pages>
        <publisher_item>
          <identifier id_type="doi">10.21105/joss.00670</identifier>
        </publisher_item>
        <ai:program name="AccessIndicators">
          <ai:license_ref applies_to="vor">http://creativecommons.org/licenses/by/4.0/</ai:license_ref>
          <ai:license_ref applies_to="am">http://creativecommons.org/licenses/by/4.0/</ai:license_ref>
          <ai:license_ref applies_to="tdm">http://creativecommons.org/licenses/by/4.0/</ai:license_ref>
        </ai:program>
        <rel:program>
          <rel:related_item>
            <rel:description>Software archive</rel:description>
            <rel:inter_work_relation relationship-type="references" identifier-type="doi">http://dx.doi.org/10.5281/zenodo.1294930</rel:inter_work_relation>
          </rel:related_item>
          <rel:related_item>
            <rel:description>GitHub review issue</rel:description>
            <rel:inter_work_relation relationship-type="hasReview" identifier-type="uri">https://github.com/openjournals/joss-reviews/issues/670</rel:inter_work_relation>
          </rel:related_item>
        </rel:program>
        <doi_data>
          <doi>10.21105/joss.00670</doi>
          <resource>http://joss.theoj.org/papers/10.21105/joss.00670</resource>
          <collection property="text-mining">
            <item>
              <resource mime_type="application/pdf">http://www.theoj.org/joss-papers/joss.00670/10.21105.joss.00670.pdf</resource>
            </item>
          </collection>
        </doi_data>
        <citation_list><citation key="ref1"><unstructured_citation>Krebber,%20Manuel, MatchPy, 2018, https://github.com/HPAC/matchpy, 2018-01-19</unstructured_citation></citation><citation key="ref2"><unstructured_citation>Barthels,%20Henrik, Linnea, 2018, https://github.com/HPAC/linnea, 2018-01-23</unstructured_citation></citation><citation key="ref3"><doi>10.7717/peerj-cs.103</doi></citation><citation key="ref4"><unstructured_citation>Wolfram%20Research,%20Inc., Mathematica, http://www.wolfram.com/mathematica/, 2018-01-19</unstructured_citation></citation><citation key="ref5"><unstructured_citation>Krebber,%20Manuel, Non-linear%20Associative-Commutative%20Many-to-One%20Pattern%20Matching%20with%20Sequence%20Variables, CoRR, abs/1705.00907, 2017, http://arxiv.org/abs/1705.00907, arXiv, 1705.00907, Wed,%2007%20Jun%202017%2014:41:51%20+0200, http://dblp.org/rec/bib/journals/corr/Krebber17, dblp%20computer%20science%20bibliography,%20http://dblp.org</unstructured_citation></citation><citation key="ref6"><doi>10.1145/3149869.3149871</doi></citation><citation key="ref7"><doi>10.25080/shinma-7f4c6e7-00b</doi></citation></citation_list>
      </journal_article>
    </journal>
  </body>
</doi_batch>
