<?xml version="1.0" encoding="UTF-8"?>
<doi_batch xmlns="http://www.crossref.org/schema/4.4.0" xmlns:ai="http://www.crossref.org/AccessIndicators.xsd" xmlns:rel="http://www.crossref.org/relations.xsd" xmlns:xsi="http://www.w3.org/2001/XMLSchema-instance" version="4.4.0" xsi:schemaLocation="http://www.crossref.org/schema/4.4.0 http://www.crossref.org/schemas/crossref4.4.0.xsd">
  <head>
    <doi_batch_id>a8d89c1ba1e0ca8439ea832eb2996f72</doi_batch_id>
    <timestamp>20201214203438</timestamp>
    <depositor>
      <depositor_name>JOSS Admin</depositor_name>
      <email_address>admin@theoj.org</email_address>
    </depositor>
    <registrant>The Open Journal</registrant>
  </head>
  <body>
    <journal>
      <journal_metadata>
        <full_title>Journal of Open Source Software</full_title>
        <abbrev_title>JOSS</abbrev_title>
        <issn media_type="electronic">2475-9066</issn>
        <doi_data>
          <doi>10.21105/joss</doi>
          <resource>https://joss.theoj.org</resource>
        </doi_data>
      </journal_metadata>
      <journal_issue>
        <publication_date media_type="online">
          <month>12</month>
          <year>2020</year>
        </publication_date>
        <journal_volume>
          <volume>5</volume>
        </journal_volume>
        <issue>56</issue>
      </journal_issue>
      <journal_article publication_type="full_text">
        <titles>
          <title>gospl: Global Scalable Paleo Landscape Evolution</title>
        </titles>
        <contributors>
          <person_name sequence="first" contributor_role="author">
            <given_name>Tristan</given_name>
            <surname>Salles</surname>
            <ORCID>http://orcid.org/0000-0001-6095-7689</ORCID>
          </person_name>
          <person_name sequence="additional" contributor_role="author">
            <given_name>Claire</given_name>
            <surname>Mallard</surname>
            <ORCID>http://orcid.org/0000-0003-2595-2414</ORCID>
          </person_name>
          <person_name sequence="additional" contributor_role="author">
            <given_name>Sabin</given_name>
            <surname>Zahirovic</surname>
            <ORCID>http://orcid.org/0000-0002-6751-4976</ORCID>
          </person_name>
        </contributors>
        <publication_date>
          <month>12</month>
          <day>14</day>
          <year>2020</year>
        </publication_date>
        <pages>
          <first_page>2804</first_page>
        </pages>
        <publisher_item>
          <identifier id_type="doi">10.21105/joss.02804</identifier>
        </publisher_item>
        <ai:program name="AccessIndicators">
          <ai:license_ref applies_to="vor">http://creativecommons.org/licenses/by/4.0/</ai:license_ref>
          <ai:license_ref applies_to="am">http://creativecommons.org/licenses/by/4.0/</ai:license_ref>
          <ai:license_ref applies_to="tdm">http://creativecommons.org/licenses/by/4.0/</ai:license_ref>
        </ai:program>
        <rel:program>
          <rel:related_item>
            <rel:description>Software archive</rel:description>
            <rel:inter_work_relation relationship-type="references" identifier-type="doi">“https://doi.org/10.5281/zenodo.4319332”</rel:inter_work_relation>
          </rel:related_item>
          <rel:related_item>
            <rel:description>GitHub review issue</rel:description>
            <rel:inter_work_relation relationship-type="hasReview" identifier-type="uri">https://github.com/openjournals/joss-reviews/issues/2804</rel:inter_work_relation>
          </rel:related_item>
        </rel:program>
        <doi_data>
          <doi>10.21105/joss.02804</doi>
          <resource>https://joss.theoj.org/papers/10.21105/joss.02804</resource>
          <collection property="text-mining">
            <item>
              <resource mime_type="application/pdf">https://joss.theoj.org/papers/10.21105/joss.02804.pdf</resource>
            </item>
          </collection>
        </doi_data>
        <citation_list>
          <citation key="ref1">
            <doi>10.1016/j.sedgeo.2018.06.007</doi>
          </citation>
          <citation key="ref2">
            <doi>10.1029/JB085iB07p03711</doi>
          </citation>
          <citation key="ref3">
            <doi>10.1029/94JB00744</doi>
          </citation>
          <citation key="ref4">
            <doi>10.1111/j.1365-2117.1992.tb00136.x</doi>
          </citation>
          <citation key="ref5">
            <doi>10.2110/jsr.2016.56</doi>
          </citation>
          <citation key="ref6">
            <doi>10.1002/2013WR014326</doi>
          </citation>
          <citation key="ref7">
            <doi>10.1016/j.cageo.2013.04.024</doi>
          </citation>
          <citation key="ref8">
            <doi>10.1016/j.epsl.2019.115728</doi>
          </citation>
          <citation key="ref9">
            <doi>10.5194/gmd-12-4165-2019</doi>
          </citation>
          <citation key="ref10">
            <doi>10.1046/j.1365-2117.1997.00030.x</doi>
          </citation>
          <citation key="ref11">
            <doi>10.1007/978-1-4615-0575-4_12</doi>
          </citation>
          <citation key="ref12">
            <doi>10.5194/esurf-5-21-2017</doi>
          </citation>
          <citation key="ref13">
            <doi>10.5194/esurf-8-379-2020</doi>
          </citation>
          <citation key="ref14">
            <doi>10.1016/j.geomorph.2012.10.008</doi>
          </citation>
          <citation key="ref15">
            <doi>10.1002/esp.1952</doi>
          </citation>
          <citation key="ref16">
            <doi>10.2110/pec.99.62.0197</doi>
          </citation>
          <citation key="ref17">
            <doi>10.1016/j.earscirev.2015.10.013</doi>
          </citation>
          <citation key="ref18">
            <unstructured_citation>Ahrens, J. and Geveci, B. and Law, C., ParaView: An End-User Tool for Large Data Visualization, Visualization Handbook, Elsevier, 2005</unstructured_citation>
          </citation>
          <citation key="ref19">
            <unstructured_citation>Barney, B., Message passing interface (MPI), Lawrence Livermore National Laboratory, 2012</unstructured_citation>
          </citation>
          <citation key="ref20">
            <doi>10.1016/j.geomorph.2015.04.007</doi>
          </citation>
          <citation key="ref21">
            <doi>10.1371/journal.pone.0195557</doi>
          </citation>
          <citation key="ref22">
            <doi>10.21105/joss.00964</doi>
          </citation>
          <citation key="ref23">
            <doi>10.1029/2010jf001935</doi>
          </citation>
          <citation key="ref24">
            <unstructured_citation>Schroeder, W. and Martin, K. and Lorensen, B., The Visualization Toolkit (4th ed.), Kitware, 2006</unstructured_citation>
          </citation>
          <citation key="ref25">
            <doi>10.1063/1.4823180</doi>
          </citation>
          <citation key="ref26">
            <unstructured_citation>The HDF Group, Hierarchical data format version 5, 2000-2010, http://www.hdfgroup.org/HDF5</unstructured_citation>
          </citation>
          <citation key="ref27">
            <unstructured_citation>Balay, S. and Brown, J. and Buschelman, K. and Gropp, W. D. and Kaushik, D. and Knepley, M. G. and McInnes, L. C. and Smith, B. F. and Zhang, H., Argonne National Laboratory, PETSc, Web page. [Available at http://www.mcs.anl.gov/petsc.], 2012</unstructured_citation>
          </citation>
          <citation key="ref28">
            <doi>10.1016/j.margeo.2011.02.014</doi>
          </citation>
        </citation_list>
      </journal_article>
    </journal>
  </body>
</doi_batch>
